mastfm/MASTFM.py
mastfm/__init__.py
mastfm/utils/ForecastingModel.py
mastfm/utils/MetaModel.py
mastfm/utils/PrepareDataset.py
mastfm/utils/TimeSeriesGenerator.py
mastfm/utils/__init__.py
mastfm-0.0.4.dist-info/licenses/LICENSE
mastfm-0.0.4.dist-info/METADATA
mastfm-0.0.4.dist-info/WHEEL
mastfm-0.0.4.dist-info/top_level.txt
mastfm-0.0.4.dist-info/RECORD
