Metadata-Version: 2.4
Name: mastfm
Version: 0.0.4
Summary: A package for Meta-learning and data Augmentation for Stress Testing Forecasting Models
Home-page: https://github.com/ricardoinaciopt/mastfm
Author: Ricardo Inácio
License: MIT
Classifier: Programming Language :: Python :: 3
Classifier: Operating System :: OS Independent
Requires-Python: >=3.8
License-File: LICENSE
Requires-Dist: numpy==1.26
Requires-Dist: pandas==2.2.2
Requires-Dist: scikit-learn>=1.5.2
Requires-Dist: shap>=0.46.0
Requires-Dist: shapiq>=1.2.3
Requires-Dist: imbalanced-learn>=0.12.4
Requires-Dist: matplotlib>=3.9.2
Requires-Dist: xgboost>=2.1.1
Requires-Dist: lightgbm>=4.5.0
Requires-Dist: tqdm
Requires-Dist: tsfeatures>=0.4.5
Requires-Dist: mlforecast>=0.13.4
Requires-Dist: metaforecast==0.1.5
Dynamic: license-file
